AUTHORS
MANIFEST.in
README.rst
setup.py
django_simple_backup.egg-info/PKG-INFO
django_simple_backup.egg-info/SOURCES.txt
django_simple_backup.egg-info/dependency_links.txt
django_simple_backup.egg-info/top_level.txt
docs/Makefile
simple_backup/__init__.py
simple_backup/signals.py
simple_backup/management/__init__.py
simple_backup/management/commands/__init__.py
simple_backup/management/commands/backup.py