Metadata-Version: 2.1
Name: django-simple-backup
Version: 2.2
Summary: A simple backup command for Django
Home-page: 
Author: Evgeny Fadeev
Author-email: evgeny.fadeev@gmail.com
Requires-Python: >2, <4
License-File: AUTHORS
